plasmid_detector/__init__.py
plasmid_detector/anomaly_detector.py
plasmid_detector/data_processor.py
plasmid_detector/feature_extractor.py
plasmid_detector/utils.py
tests/__init__.py
tests/test_anomaly_detector.py
tests/test_data_processor.py
tests/test_feature_extractor.py
plasmid_detector-0.1.0.dist-info/METADATA
plasmid_detector-0.1.0.dist-info/WHEEL
plasmid_detector-0.1.0.dist-info/entry_points.txt
plasmid_detector-0.1.0.dist-info/top_level.txt
plasmid_detector-0.1.0.dist-info/RECORD
