Metadata-Version: 2.1
Name: plasmid_detector
Version: 0.1.0
Requires-Dist: numpy
Requires-Dist: pandas
Requires-Dist: scikit-learn
Requires-Dist: scipy
Requires-Dist: matplotlib
